chiloc
