Metadata-Version: 1.0
Name: chiloc
Version: 1.0.2
Summary: Chinese Location Finder
Home-page: UNKNOWN
Author: UNKNOWN
Author-email: UNKNOWN
License: UNKNOWN
Platform: UNKNOWN
